pyNutFtp/__init__.py
pyNutFtp/_lib.py
pyNutFtp/nutFtp.py
pynut_ftp-2.1.5.dist-info/LICENSE
pynut_ftp-2.1.5.dist-info/METADATA
pynut_ftp-2.1.5.dist-info/WHEEL
pynut_ftp-2.1.5.dist-info/top_level.txt
pynut_ftp-2.1.5.dist-info/RECORD
