Metadata-Version: 2.1
Name: pynut-ftp
Version: 2.1.5
Summary: Function easing life :)
Home-page: https://github.com/Laurent-Tupin/pynut_DB
Author: Laurent Tupin
Author-email: laurent.tupinn@gmail.com
License: Copyright 2022-2035
Platform: UNKNOWN
Classifier: License :: Free For Home Use
Classifier: Programming Language :: Python :: 3
Classifier: Programming Language :: Python :: 3.9
License-File: LICENSE
Requires-Dist: pynut-Files (==2.2.4)
Requires-Dist: paramiko (==2.11.0)
Requires-Dist: pysftp (==0.2.9)
